hassapi/__init__.py
hassapi/__main__.py
hassapi/const.py
hassapi/exceptions.py
hassapi/version.py
hassapi/client/__init__.py
hassapi/client/auth.py
hassapi/client/base.py
hassapi/client/events.py
hassapi/client/services.py
hassapi/client/states.py
hassapi/client/template.py
hassapi/models/__init__.py
hassapi/models/base.py
hassapi/models/event.py
hassapi/models/service.py
hassapi/models/state.py
hassapi-0.2.1.dist-info/LICENSE
hassapi-0.2.1.dist-info/METADATA
hassapi-0.2.1.dist-info/WHEEL
hassapi-0.2.1.dist-info/top_level.txt
hassapi-0.2.1.dist-info/RECORD
